{
  "id": "SRC-MALTA-0013",
  "place_code": "MALTA",
  "created_at": "2026-02-23",
  "bundle_ref_nums": [],
  "title": "Ħal Saflieni Hypogeum (Heritage Malta Official)",
  "author": "Heritage Malta",
  "date_or_year": "2024",
  "medium": "Offizielle Webseite/Museumsführer",
  "url": "https://heritagemalta.mt/explore/hal-saflieni-hypogeum/",
  "source_type": "official_site",
  "reliability_tier": "A",
  "epistemic_notes": "DP-002: treat metaphysical/causal claims as claims; encode as frames, not facts."
}
